{
    "!": "",
    "\"": "",
    "#": "",
    "$": "",
    "%": "",
    "&": " ___  ___   ___  ___   ___         __          ___     ___   ___                                 ___  ___  ___   ___                          ___         ___     \n`._|=|   |=|_.' |   | |   |   .'|=|  |    .'|=|_.'    |   |=|_.'   .'|=|`.     .'|\\/|`.     .'|=|_.' `._|=|   |=|_.'   .'| |`.     .'|   .'| |   |   .'|=|_.'     \n     |   |      `.  |_|  .' .'  | |  |  .'  |  ___    `.  |      .'  | |  `. .'  |  |  `. .'  |  ___      |   |      .'  | |  `. .'  | .'  |\\|   | .'  |___       \n     |   |        `.   .'   |   |=|.'   |   |=|_.'      `.|=|`.  |   | |   | |   |  |   | |   |=|_.'      |   |      |   |=|   | |   | |   | |   | |   |`._|=.    \n     `.  |         |   |    |   |       |   |  ___     ___  |  `.`.  | |  .' |   |  |   | |   |  ___      `.  |      |   | |   | |   | |   | |  .' `.  |  __||    \n       `.|         |___|    |___|       |___|=|_.'     `._|=|___|  `.|=|.'   |___|  |___| |___|=|_.'        `.|      |___| |___| |___| |___| |.'     `.|=|_.''    \n                                                                                                                                                                  ",
    "'": "",
    "(": "",
    ")": "",
    "*": "",
    "+": "",
    ",": "    \n    \n    \n    \n.-. \n`/' \n    ",
    "-": "",
    ".": "    \n    \n    \n    \n.-. \n`-' \n    ",
    "/": "",
    "0": "            \n  .'|=|`.   \n.'  | |  `. \n|   |/|   | \n`.  | |  .' \n  `.|=|.'   \n            ",
    "1": " ______  \n`._    | \n   |   | \n   |   | \n   |   | \n   |___| \n         ",
    "2": " ___        \n `._|=|`.   \n      |  `. \n  .'|=|___| \n.'  |  ___  \n|___|=|_.'  \n            ",
    "3": " ___        \n `._|=|`.   \n ___  |  `. \n `._|=|   | \n ___  |   | \n `._|=|___| \n            ",
    "4": "           \n|`.  |`.   \n|  | |  `. \n|__|=|   | \n     |   | \n     |___| \n           ",
    "5": " ___   ___  \n|   |=|_.'  \n|   |       \n|___|=|`.   \n ___  |  `. \n `._|=|___| \n            ",
    "6": "       ___ \n  .'|=|_.' \n.'  |      \n|   |=|`.  \n|   | |  | \n|___|=|__| \n           ",
    "7": " ___   ___  \n `._|=|   | \n      |  .' \n  .'|=|.'   \n.'  |       \n|___|       \n            ",
    "8": "  __   __   \n.'  |=|  `. \n`.  | |  .' \n .` |=| `.  \n|   | |   | \n`.__|=|__.' \n            ",
    "9": " __        \n|  |=|`.   \n|  | |  `. \n `.|=|   | \n___  |   | \n`._|=|___| \n           ",
    ":": "    \n.-. \n`-' \n    \n.-. \n`-' \n    ",
    ";": "    \n.-. \n`-' \n    \n.-. \n`/' \n    ",
    "<": "",
    "=": " ___  ___   ___  ___   ___         __          ___     ___   ___                                 ___  ___  ___   ___                          ___         ___     \n`._|=|   |=|_.' |   | |   |   .'|=|  |    .'|=|_.'    |   |=|_.'   .'|=|`.     .'|\\/|`.     .'|=|_.' `._|=|   |=|_.'   .'| |`.     .'|   .'| |   |   .'|=|_.'     \n     |   |      `.  |_|  .' .'  | |  |  .'  |  ___    `.  |      .'  | |  `. .'  |  |  `. .'  |  ___      |   |      .'  | |  `. .'  | .'  |\\|   | .'  |___       \n     |   |        `.   .'   |   |=|.'   |   |=|_.'      `.|=|`.  |   | |   | |   |  |   | |   |=|_.'      |   |      |   |=|   | |   | |   | |   | |   |`._|=.    \n     `.  |         |   |    |   |       |   |  ___     ___  |  `.`.  | |  .' |   |  |   | |   |  ___      `.  |      |   | |   | |   | |   | |  .' `.  |  __||    \n       `.|         |___|    |___|       |___|=|_.'     `._|=|___|  `.|=|.'   |___|  |___| |___|=|_.'        `.|      |___| |___| |___| |___| |.'     `.|=|_.''    \n                                                                                                                                                                  ",
    ">": "",
    "?": "",
    "@": "",
    "A": "            \n  .'|=|`.   \n.'  | |  `. \n|   |=|   | \n|   | |   | \n|___| |___| \n            ",
    "B": "       _   \n  .'|=| `. \n.'  | | .' \n|   |=|'.  \n|   | |  | \n|___|=|_.' \n           ",
    "C": "       ___ \n  .'|=|_.' \n.'  |      \n|   |      \n`.  |  ___ \n  `.|=|_.' \n           ",
    "D": "            \n  .'|=|`.   \n.'  | |  `. \n|   | |   | \n|   | |  .' \n|___|=|.'   \n            ",
    "E": "       ___ \n  .'|=|_.' \n.'  |  ___ \n|   |=|_.' \n|   |  ___ \n|___|=|_.' \n           ",
    "F": "       ___ \n  .'|=|_.' \n.'  |  ___ \n|   |=|_.' \n|   |      \n|___|      \n           ",
    "G": "       ___  \n  .'|=|_.'  \n.'  |___    \n|   |`._|=. \n`.  |  __|| \n  `.|=|_.'' \n            ",
    "H": "            \n  .'| |`.   \n.'  | |  `. \n|   |=|   | \n|   | |   | \n|___| |___| \n            ",
    "I": "      \n  .'| \n.'  | \n|   | \n|   | \n|___| \n      ",
    "J": "           \n       .'| \n     .'  | \n     |   | \n___  |   | \n`._|=|__.' \n           ",
    "K": "            \n  .'|   .'| \n.'  | .' .' \n|   |=|.:   \n|   |   |'. \n|___|   |_| \n            ",
    "L": "           \n  .'|      \n.'  |      \n|   |      \n|   |  ___ \n|___|=|_.' \n           ",
    "M": "             \n  .'|\\/|`.   \n.'  |  |  `. \n|   |  |   | \n|   |  |   | \n|___|  |___| \n             ",
    "N": "       ___  \n  .'| |   | \n.'  |\\|   | \n|   | |   | \n|   | |  .' \n|___| |.'   \n            ",
    "O": "            \n  .'|=|`.   \n.'  | |  `. \n|   | |   | \n`.  | |  .' \n  `.|=|.'   \n            ",
    "P": "       __   \n  .'|=|  |  \n.'  | |  |  \n|   |=|.'   \n|   |       \n|___|       \n            ",
    "Q": "            \n  .'|=|`.   \n.'  | |  `. \n|   |\\|   | \n`.  | |  .' \n  `.|=|.'\\  \n            ",
    "R": "       __  \n  .'|=|  | \n.'  | |  | \n|   |=|.'  \n|   |  |`. \n|___|  |_| \n           ",
    "S": " ___   ___ \n|   |=|_.' \n`.  |      \n  `.|=|`.  \n ___  |  `.\n `._|=|___|\n           ",
    "T": " ___  ___   ___ \n`._|=|   |=|_.' \n     |   |      \n     |   |      \n     `.  |      \n       `.|      \n                ",
    "U": " ___        \n|   | |`.   \n|   | |  `. \n|   | |   | \n`.  | |   | \n  `.|=|___| \n            ",
    "V": " ___   ___  \n|   | |   | \n|   | |   | \n|   | |   | \n`.  | |  .' \n  `.|=|.'   \n            ",
    "W": " ___    ___  \n|   |  |   | \n|   |  |   | \n|   |  |   | \n`.  |  |  .' \n  `.|/\\|.'   \n             ",
    "X": " ___   ___  \n|   | |   | \n`.  | |  .' \n .` |=| `.  \n|   | |   | \n|___| |___| \n            ",
    "Y": " ___   ___  \n|   | |   | \n`.  |_|  .' \n  `.   .'   \n   |   |    \n   |___|    \n            ",
    "Z": " ___   ___  \n `._|=|   | \n      |  .' \n  .'|=|.'   \n.'  |  ___  \n|___|=|_.'  \n            ",
    "[": "",
    "\\": "",
    "]": "",
    "^": "",
    "_": "",
    "`": "",
    "a": "            \n  .'|=|`.   \n.'  | |  `. \n|   |=|   | \n|   | |   | \n|___| |___| \n            ",
    "b": "       _   \n  .'|=| `. \n.'  | | .' \n|   |=|'.  \n|   | |  | \n|___|=|_.' \n           ",
    "c": "       ___ \n  .'|=|_.' \n.'  |      \n|   |      \n`.  |  ___ \n  `.|=|_.' \n           ",
    "d": "            \n  .'|=|`.   \n.'  | |  `. \n|   | |   | \n|   | |  .' \n|___|=|.'   \n            ",
    "e": "       ___ \n  .'|=|_.' \n.'  |  ___ \n|   |=|_.' \n|   |  ___ \n|___|=|_.' \n           ",
    "f": "       ___ \n  .'|=|_.' \n.'  |  ___ \n|   |=|_.' \n|   |      \n|___|      \n           ",
    "g": "       ___  \n  .'|=|_.'  \n.'  |___    \n|   |`._|=. \n`.  |  __|| \n  `.|=|_.'' \n            ",
    "h": "            \n  .'| |`.   \n.'  | |  `. \n|   |=|   | \n|   | |   | \n|___| |___| \n            ",
    "i": "      \n  .'| \n.'  | \n|   | \n|   | \n|___| \n      ",
    "j": "           \n       .'| \n     .'  | \n     |   | \n___  |   | \n`._|=|__.' \n           ",
    "k": "            \n  .'|   .'| \n.'  | .' .' \n|   |=|.:   \n|   |   |'. \n|___|   |_| \n            ",
    "l": "           \n  .'|      \n.'  |      \n|   |      \n|   |  ___ \n|___|=|_.' \n           ",
    "m": "             \n  .'|\\/|`.   \n.'  |  |  `. \n|   |  |   | \n|   |  |   | \n|___|  |___| \n             ",
    "n": "       ___  \n  .'| |   | \n.'  |\\|   | \n|   | |   | \n|   | |  .' \n|___| |.'   \n            ",
    "o": "            \n  .'|=|`.   \n.'  | |  `. \n|   | |   | \n`.  | |  .' \n  `.|=|.'   \n            ",
    "p": "       __   \n  .'|=|  |  \n.'  | |  |  \n|   |=|.'   \n|   |       \n|___|       \n            ",
    "q": "            \n  .'|=|`.   \n.'  | |  `. \n|   |\\|   | \n`.  | |  .' \n  `.|=|.'\\  \n            ",
    "r": "       __  \n  .'|=|  | \n.'  | |  | \n|   |=|.'  \n|   |  |`. \n|___|  |_| \n           ",
    "s": " ___   ___ \n|   |=|_.' \n`.  |      \n  `.|=|`.  \n ___  |  `.\n `._|=|___|\n           ",
    "t": " ___  ___   ___ \n`._|=|   |=|_.' \n     |   |      \n     |   |      \n     `.  |      \n       `.|      \n                ",
    "u": " ___        \n|   | |`.   \n|   | |  `. \n|   | |   | \n`.  | |   | \n  `.|=|___| \n            ",
    "v": " ___   ___  \n|   | |   | \n|   | |   | \n|   | |   | \n`.  | |  .' \n  `.|=|.'   \n            ",
    "w": " ___    ___  \n|   |  |   | \n|   |  |   | \n|   |  |   | \n`.  |  |  .' \n  `.|/\\|.'   \n             ",
    "x": " ___   ___  \n|   | |   | \n`.  | |  .' \n .` |=| `.  \n|   | |   | \n|___| |___| \n            ",
    "y": " ___   ___  \n|   | |   | \n`.  |_|  .' \n  `.   .'   \n   |   |    \n   |___|    \n            ",
    "z": " ___   ___  \n `._|=|   | \n      |  .' \n  .'|=|.'   \n.'  |  ___  \n|___|=|_.'  \n            ",
    "{": "",
    "|": "",
    "}": "",
    "~": ""
}